mnncompress/__init__.py
mnncompress/version.py
mnncompress/common/MNN_compression_pb2.py
mnncompress/common/VBMF.py
mnncompress/common/__init__.py
mnncompress/common/helper.py
mnncompress/common/log.py
mnncompress/pytorch/LSQ_quantizer.py
mnncompress/pytorch/SIMD_OC_pruner.py
mnncompress/pytorch/SNIP_level_pruner.py
mnncompress/pytorch/TaylorFO_channel_pruner.py
mnncompress/pytorch/__init__.py
mnncompress/pytorch/compute_new_weights.py
mnncompress/pytorch/decomposition.py
mnncompress/pytorch/linear_over_param.py
mnncompress/pytorch/utils.py
mnncompress/pytorch/weight_quantizer.py
mnncompress/tensorflow/EMA_quantizer.py
mnncompress/tensorflow/LSQ_quantizer.py
mnncompress/tensorflow/OAQ_quantizer.py
mnncompress/tensorflow/SA_prune_ratio_searcher.py
mnncompress/tensorflow/SIMD_OC_pruner.py
mnncompress/tensorflow/SNIP_level_pruner.py
mnncompress/tensorflow/TaylorFO_channel_pruner.py
mnncompress/tensorflow/__init__.py
mnncompress/tensorflow/admm_pruner.py
mnncompress/tensorflow/decomposition.py
mnncompress/tensorflow/fix_quant_params.py
mnncompress/tensorflow/graph_checker.py
mnncompress/tensorflow/helpers.py
mnncompress/tensorflow/hooks.py
mnncompress/tensorflow/level_pruner.py
mnncompress/tensorflow/overflow_custom_ops.py
mnncompress/tensorflow/sensitivity_analyzer.py
mnncompress/tensorflow/weight_quantizer.py
mnncompress-0.3.2.dist-info/METADATA
mnncompress-0.3.2.dist-info/WHEEL
mnncompress-0.3.2.dist-info/top_level.txt
mnncompress-0.3.2.dist-info/RECORD
