Metadata-Version: 2.1
Name: mnncompress
Version: 0.3.2
Summary: model comprssion tools for MNN
Home-page: https://github.com/alibaba/MNN
Author: Yang Yafeng
Author-email: nickyoung.yyf@alibaba-inc.com
License: UNKNOWN
Platform: any
Requires-Dist: aliyun-log-python-sdk
Requires-Dist: tensorly (==0.4.5)
